tefas/__init__.py
tefas/program.py
tefas-1.0.1.dist-info/METADATA
tefas-1.0.1.dist-info/WHEEL
tefas-1.0.1.dist-info/top_level.txt
tefas-1.0.1.dist-info/RECORD
