Metadata-Version: 2.1
Name: tefas
Version: 1.0.1
Summary: Extract text from a YouTube video in a single command, using OpenAi's Whisper speech recognition model
Home-page: https://github.com/atahanuz/tefas
Author: Atahan Uz
Author-email: atahanuz23@gmail.com
Classifier: Programming Language :: Python :: 3
Classifier: License :: OSI Approved :: MIT License
Classifier: Operating System :: OS Independent
